skytop.py
skytop-0.1.0.dist-info/WHEEL
skytop-0.1.0.dist-info/METADATA
skytop-0.1.0.dist-info/RECORD
