Metadata-Version: 2.1
Name: skytop
Version: 0.1.0
Summary: 
Home-page: https://www.sky.top/
License: MIT
Author: SkyTop
Requires-Python: >=3.7,<4.0
Classifier: License :: OSI Approved :: MIT License
Classifier: Programming Language :: Python :: 3
Classifier: Programming Language :: Python :: 3.10
Classifier: Programming Language :: Python :: 3.7
Classifier: Programming Language :: Python :: 3.8
Classifier: Programming Language :: Python :: 3.9
Requires-Dist: requests (==2.27.1)
Project-URL: Repository, https://github.com/SkyTopCo/skytop-py
